j2pipeline/__init__.py
j2pipeline/tcp/__init__.py
j2pipeline/tcp/client.py
j2pipeline/tcp/manager.py
j2pipeline/template/__init__.py
j2pipeline/template/load.py
j2pipeline/template/render.py
j2pipeline/template/vars.py
j2pipeline/types/__init__.py
j2pipeline/types/pipeline.py
j2pipeline/types/prompt.py
j2pipeline-0.4.0.dist-info/LICENSE.txt
j2pipeline-0.4.0.dist-info/METADATA
j2pipeline-0.4.0.dist-info/WHEEL
j2pipeline-0.4.0.dist-info/top_level.txt
j2pipeline-0.4.0.dist-info/RECORD
